 [
    {
        "id":1,
        "cover":"/img/alone1.jpg",
        "titleGallery":"alone",
    
        "pictures": [{
            "styles":"m-5 rounded-xl max-w-[350px] h-[350px] md:w-[500px]",
            "photo":"/img/alone1.jpg"
        },{
            "styles":"m-5 rounded-xl max-w-[350px] h-[350px] md:w-[500px]",
            "photo":"/img/alone1.jpg"
        },
        {
            "styles":"m-5 rounded-xl  w-[350px] h-[500px]",
            "photo":"/img/alone2.png"
        },
        {
            "styles":"m-5 rounded-xl w-[350px] h-[500px]",
            "photo":"/img/alone2.png"
        }  

        ]

    },
    {
        "id":2,
        "cover":"/img/flou2.jpg",
        "titleGallery":"flou",
        "pictures": [
            {"styles":"m-5 rounded-xl  w-[350px] h-[500px]",
            "photo":"/img/flou1.jpg"
            },
            {"styles":"m-5 rounded-xl  w-[350px] h-[500px]",
            "photo":"/img/flou2.jpg"
            }
        ]

    },
    {
        "id":3,
        "cover":"/img/refuge1.jpg",
        "titleGallery":"refuge",
        "pictures": [
            {
            "styles":"m-5 rounded-xl w-[350px] h-[500px]",
            "photo":"/img/refuge2.jpg"
            },
            {
            "styles":"m-5 rounded-xl w-[500px] h-[350px]",
            "photo":"/img/refuge3.jpg"
            },
             {
            "styles":"m-5 rounded-xl w-[350px] h-[500px]",
            "photo":"/img/refuge1.jpg"
            }, 
            {
            "styles":"m-5 rounded-xl w-[350px] h-[500px]",
            "photo":"/img/refuge4.jpg"
            }
        
            
        ]

    },
    {
        "id":4,
        "cover":"/img/plante2.jpg",
        "titleGallery":"plants",
        "pictures": [
            {
            "styles":"m-5 rounded-xl w-[350px] h-[500px]",
            "photo":"/img/plante4.jpg"
            },
            {
            "styles":"m-5 rounded-xl w-[350px] h-[500px]",
            "photo":"/img/plante1.jpg"
            },
            {
            "styles":"m-5 rounded-xl w-[350px] h-[500px]",
            "photo":"/img/plante2.jpg"
            }  
        ]
    },    
    {
        "id":5,
        "cover":"/img/vehicule2.jpg",
        "titleGallery":"véhicules",
        "pictures": [
            {
               "styles":"m-5 rounded-xl w-[500px] h-[350px]",
            "photo": "/img/vehicule1.jpg"
            },
            {
                "styles":"m-5 rounded-xl w-[500px] h-[350px]",
            "photo":"/img/vehicule2.jpg"
            },
            {
                "styles":"m-5 rounded-xl w-[350px] h-[500px]",
            "photo":"/img/vehicule3.jpg"
            } 
        ]

    },
    
    {
        "id":6,
        "cover":"/img/natureenville2.jpg",
        "titleGallery":"nature en ville",
        "pictures": [
            {"styles":"m-5 rounded-xl w-[500px] h-[350px]",
            "photo":"/img/natureenville3.jpg"
            },
            {"styles":"m-5 rounded-xl w-[500px] h-[350px]",
            "photo":"/img/natureenville2.jpg"
            }  
        ]

    },
    
    {
        "id":7,
        "cover":"/img/message1.jpg",
        "titleGallery":"message",
        "pictures": [
            
            {
            "styles":"m-5 rounded-xl w-[500px] h-[350px]",
            "photo":"/img/message2.jpg"
            },
            {
            "styles":"m-5 rounded-xl w-[350px] h-[500px]",
            "photo":"/img/message1.jpg"
            }
            
        ]

    },
    
    {
        "id":8,
        "cover":"/img/bazar1.jpg",
        "titleGallery":"bazar",
        "pictures": [
            {
                "styles":"m-5 rounded-xl w-[500px] h-[350px]",
            "photo":"/img/bazar1.jpg"
            },
            {
            "styles":"m-5 rounded-xl w-[500px] h-[350px]",
            "photo":"/img/bazar2.jpg"
            }
            
        ]

    }
]